mockpy/__init__.py
mockpy/mockpy.py
mockpy/version.py
mockpy/core/__init__.py
mockpy/core/cherrypy_mapper.py
mockpy/core/cherrypy_server.py
mockpy/core/proxy_mapper.py
mockpy/core/proxy_server.py
mockpy/data/sample.yml
mockpy/models/__init__.py
mockpy/models/mapping_item.py
mockpy/models/mapping_items_manager.py
mockpy/models/mapping_request.py
mockpy/models/mapping_respone.py
mockpy/status/__init__.py
mockpy/status/status.py
mockpy/utils/__init__.py
mockpy/utils/args_parser.py
mockpy/utils/cherrypy_extensions.py
mockpy/utils/config.py
mockpy/utils/dir_init.py
mockpy/utils/log.py
mockpy/utils/network.py
mockpy/utils/proxy_extensions.py
mockpy-0.1.7.dist-info/DESCRIPTION.rst
mockpy-0.1.7.dist-info/entry_points.txt
mockpy-0.1.7.dist-info/METADATA
mockpy-0.1.7.dist-info/metadata.json
mockpy-0.1.7.dist-info/RECORD
mockpy-0.1.7.dist-info/top_level.txt
mockpy-0.1.7.dist-info/WHEEL
