Metadata-Version: 2.0
Name: mockpy
Version: 0.1.7
Summary: Mockpy is a python open source line utility to quickly create mock servers on Mac OS X.
Home-page: https://github.com/oarrabi/mockpy
Author: Omar Abdelhafith
Author-email: o.arrabi@me.com
License: BSD
Keywords: mockpy
Platform: UNKNOWN
Classifier: Development Status :: 2 - Pre-Alpha
Classifier: Intended Audience :: Developers
Classifier: License :: OSI Approved :: BSD License
Classifier: Natural Language :: English
Classifier: Programming Language :: Python :: 2
Classifier: Programming Language :: Python :: 2.6
Classifier: Programming Language :: Python :: 2.7
Requires-Dist: mock
Requires-Dist: cherrypy
Requires-Dist: termcolor
Requires-Dist: watchdog
Requires-Dist: netlib
Requires-Dist: mitmproxy
